_edi_energy_scraper_version.py
edi_energy_scraper/__init__.py
edi_energy_scraper/apidocument.py
edi_energy_scraper/documentmetadata.py
edi_energy_scraper/py.typed
edi_energy_scraper/scraper.py
edi_energy_scraper/utilities.py
edi_energy_scraper-2.2.3.dist-info/METADATA
edi_energy_scraper-2.2.3.dist-info/WHEEL
edi_energy_scraper-2.2.3.dist-info/licenses/LICENSE
edi_energy_scraper-2.2.3.dist-info/RECORD
