Metadata-Version: 2.4
Name: edi_energy_scraper
Version: 2.2.3
Summary: a scraper to mirror edi-energy.de
Project-URL: Changelog, https://github.com/Hochfrequenz/edi_energy_scraper/releases
Project-URL: Homepage, https://github.com/Hochfrequenz/edi_energy_scraper
Author-email: Hochfrequenz Unternehmensberatung GmbH <info+github@hochfrequenz.de>
License: MIT
License-File: LICENSE
Keywords: ahb,automation,bdew,bdew-mako.de,edi@energy
Classifier: Development Status :: 5 - Production/Stable
Classifier: Environment :: Console
Classifier: Intended Audience :: Developers
Classifier: License :: OSI Approved :: MIT License
Classifier: Operating System :: OS Independent
Classifier: Programming Language :: Python
Classifier: Programming Language :: Python :: 3 :: Only
Classifier: Programming Language :: Python :: 3.10
Classifier: Programming Language :: Python :: 3.11
Classifier: Programming Language :: Python :: 3.12
Classifier: Programming Language :: Python :: 3.13
Classifier: Programming Language :: Python :: 3.14
Requires-Python: >=3.10
Requires-Dist: aiohttp>=3.8.4
Requires-Dist: efoli>=2.1.0
Requires-Dist: more-itertools
Requires-Dist: pydantic>=2
Requires-Dist: pypdf>=3.4.1
Requires-Dist: pytz>=2022.7.1
Requires-Dist: pytz>=2024.2
Provides-Extra: coverage
Requires-Dist: coverage==7.10.7; extra == 'coverage'
Provides-Extra: formatting
Requires-Dist: black==25.9.0; extra == 'formatting'
Requires-Dist: isort==7.0.0; extra == 'formatting'
Provides-Extra: linting
Requires-Dist: pylint==3.3.7; extra == 'linting'
Provides-Extra: spellcheck
Requires-Dist: codespell==2.4.1; extra == 'spellcheck'
Provides-Extra: test-packaging
Requires-Dist: build==1.3.0; extra == 'test-packaging'
Requires-Dist: twine==6.2.0; extra == 'test-packaging'
Provides-Extra: tests
Requires-Dist: aioresponses==0.7.8; extra == 'tests'
Requires-Dist: freezegun==1.5.5; extra == 'tests'
Requires-Dist: pytest-asyncio==1.2.0; extra == 'tests'
Requires-Dist: pytest-mock==3.14.1; extra == 'tests'
Requires-Dist: pytest==8.4.2; extra == 'tests'
Requires-Dist: syrupy==4.9.1; extra == 'tests'
Provides-Extra: type-check
Requires-Dist: mypy==1.17.1; extra == 'type-check'
Requires-Dist: types-pytz==2025.2.0.20250516; extra == 'type-check'
